{
  "$schema": "http://json-schema.org/draft-04/schema#",
  "additionalProperties": false,
  "id": "yadage_stage",
  "items": {
    "properties": {
      "files": {
        "properties": {
          "bkg_mcinfo": {
            "items": {
              "properties": {
                "inputfiles": {
                  "items": {
                    "type": "string"
                  },
                  "title": "Background Input Files",
                  "type": "array"
                },
                "name": {
                  "type": "string"
                },
                "weight": {
                  "type": "number"
                }
              },
              "type": "object"
            },
            "title": "Background MC Info",
            "type": "array"
          },
          "data_inputfiles": {
            "items": {
              "type": "string"
            },
            "title": "Data Input Files",
            "type": "array"
          },
          "signal_inputfiles": {
            "items": {
              "type": "string"
            },
            "title": "Signal Input Files",
            "type": "array"
          },
          "signal_mcweight": {
            "title": "Signal MC Weight",
            "type": "number"
          }
        },
        "title": "Files",
        "type": "object"
      },
      "title": {
        "title": "Name",
        "type": "string"
      }
    },
    "type": "object"
  },
  "title": "Inputs",
  "type": "array"
}
