{
    "title": "airbnb-averages@public",
    "type": "object",
    "oneOf": [
        {
            "$ref": "#/definitions/airbnb-averages@public"
        }
    ],
    "definitions": {
        "airbnb-averages@public": {
            "properties": {
                "records": {
                    "type": "array",
                    "items": {
                        "$ref": "#/definitions/airbnb-averages@public_records"
                    }
                }
            }
        },
        "geoJSON": {
            "title": "Geo JSON object",
            "description": "Schema for a Geo JSON object",
            "type": "object",
            "required": [
                "type"
            ],
            "properties": {
                "crs": {
                    "$ref": "#/definitions/crs"
                },
                "bbox": {
                    "$ref": "#/definitions/bbox"
                }
            },
            "oneOf": [
                {
                    "$ref": "#/definitions/geometry"
                },
                {
                    "$ref": "#/definitions/geometryCollection"
                },
                {
                    "$ref": "#/definitions/feature"
                },
                {
                    "$ref": "#/definitions/featureCollection"
                }
            ]
        },
        "bbox": {
            "description": "A bounding box as defined by GeoJSON",
            "type": "array",
            "items": {
                "type": "number"
            }
        },
        "crs": {
            "title": "crs",
            "description": "a Coordinate Reference System object",
            "type": [
                "object",
                "null"
            ],
            "required": [
                "type",
                "properties"
            ],
            "properties": {
                "type": {
                    "type": "string"
                },
                "properties": {
                    "type": "object"
                }
            },
            "additionalProperties": false,
            "oneOf": [
                {
                    "$ref": "#/definitions/namedCrs"
                },
                {
                    "$ref": "#/definitions/linkedCrs"
                }
            ]
        },
        "namedCrs": {
            "properties": {
                "type": {
                    "enum": [
                        "name"
                    ]
                },
                "properties": {
                    "required": [
                        "name"
                    ],
                    "additionalProperties": false,
                    "properties": {
                        "name": {
                            "type": "string"
                        }
                    }
                }
            }
        },
        "linkedObject": {
            "type": "object",
            "required": [
                "href"
            ],
            "properties": {
                "href": {
                    "type": "string",
                    "format": "uri"
                },
                "type": {
                    "type": "string",
                    "description": "Suggested values: proj4, ogjwkt, esriwkt"
                }
            }
        },
        "linkedCrs": {
            "properties": {
                "type": {
                    "enum": [
                        "link"
                    ]
                },
                "properties": {
                    "$ref": "#/definitions/linkedObject"
                }
            }
        },
        "geometryCollection": {
            "title": "GeometryCollection",
            "description": "A collection of geometry objects",
            "required": [
                "geometries"
            ],
            "properties": {
                "type": {
                    "enum": [
                        "GeometryCollection"
                    ]
                },
                "geometries": {
                    "type": "array",
                    "items": {
                        "$ref": "http://json-schema.org/geojson/geometry.json#"
                    }
                }
            }
        },
        "feature": {
            "title": "Feature",
            "description": "A Geo JSON feature object",
            "required": [
                "geometry",
                "properties"
            ],
            "properties": {
                "type": {
                    "enum": [
                        "Feature"
                    ]
                },
                "geometry": {
                    "oneOf": [
                        {
                            "type": "null"
                        },
                        {
                            "$ref": "#/definitions/geometry"
                        }
                    ]
                },
                "properties": {
                    "type": [
                        "object",
                        "null"
                    ]
                },
                "id": {}
            }
        },
        "featureCollection": {
            "title": "FeatureCollection",
            "description": "A Geo JSON feature collection",
            "required": [
                "features"
            ],
            "properties": {
                "type": {
                    "enum": [
                        "FeatureCollection"
                    ]
                },
                "features": {
                    "type": "array",
                    "items": {
                        "$ref": "#/definitions/feature"
                    }
                }
            }
        },
        "geometry": {
            "title": "geometry",
            "description": "One geometry as defined by GeoJSON",
            "type": "object",
            "required": [
                "type",
                "coordinates"
            ],
            "oneOf": [
                {
                    "title": "Point",
                    "properties": {
                        "type": {
                            "enum": [
                                "Point"
                            ]
                        },
                        "coordinates": {
                            "$ref": "#/definitions/position"
                        }
                    }
                },
                {
                    "title": "MultiPoint",
                    "properties": {
                        "type": {
                            "enum": [
                                "MultiPoint"
                            ]
                        },
                        "coordinates": {
                            "$ref": "#/definitions/positionArray"
                        }
                    }
                },
                {
                    "title": "LineString",
                    "properties": {
                        "type": {
                            "enum": [
                                "LineString"
                            ]
                        },
                        "coordinates": {
                            "$ref": "#/definitions/lineString"
                        }
                    }
                },
                {
                    "title": "MultiLineString",
                    "properties": {
                        "type": {
                            "enum": [
                                "MultiLineString"
                            ]
                        },
                        "coordinates": {
                            "type": "array",
                            "items": {
                                "$ref": "#/definitions/lineString"
                            }
                        }
                    }
                },
                {
                    "title": "Polygon",
                    "properties": {
                        "type": {
                            "enum": [
                                "Polygon"
                            ]
                        },
                        "coordinates": {
                            "$ref": "#/definitions/polygon"
                        }
                    }
                },
                {
                    "title": "MultiPolygon",
                    "properties": {
                        "type": {
                            "enum": [
                                "MultiPolygon"
                            ]
                        },
                        "coordinates": {
                            "type": "array",
                            "items": {
                                "$ref": "#/definitions/polygon"
                            }
                        }
                    }
                }
            ],
            "position": {
                "description": "A single position",
                "type": "array",
                "minItems": 2,
                "items": [
                    {
                        "type": "number"
                    },
                    {
                        "type": "number"
                    }
                ],
                "additionalItems": false
            },
            "positionArray": {
                "description": "An array of positions",
                "type": "array",
                "items": {
                    "$ref": "#/definitions/position"
                }
            },
            "lineString": {
                "description": "An array of two or more positions",
                "allOf": [
                    {
                        "$ref": "#/definitions/positionArray"
                    },
                    {
                        "minItems": 2
                    }
                ]
            },
            "linearRing": {
                "description": "An array of four positions where the first equals the last",
                "allOf": [
                    {
                        "$ref": "#/definitions/positionArray"
                    },
                    {
                        "minItems": 4
                    }
                ]
            },
            "polygon": {
                "description": "An array of linear rings",
                "type": "array",
                "items": {
                    "$ref": "#/definitions/linearRing"
                }
            }
        },
        "airbnb-averages@public_records": {
            "properties": {
                "fields": {
                    "type": "object",
                    "properties": {
                        "neighbourhood": {
                            "type": "string",
                            "title": "Neighbourhood",
                            "description": ""
                        },
                        "room_type": {
                            "type": "string",
                            "title": "Accommodation type",
                            "description": ""
                        },
                        "number_of_rooms": {
                            "type": "integer",
                            "title": "Number of accommodations",
                            "description": "Number of accommodations in the neighbourhood"
                        },
                        "price": {
                            "type": "number",
                            "title": "Room price per night",
                            "description": "Average room price for the neighbourhood and the accomodation type"
                        },
                        "reviews_per_month": {
                            "type": "number",
                            "title": "Reviews per month",
                            "description": "Average number of reviews per month for the neighbourhood and the accomodation type"
                        },
                        "calculated_host_listings_count": {
                            "type": "number",
                            "title": "Host listing counts",
                            "description": "Average number of accommodations per host (for hosts who have an accommodation of this type in this neighbourhood)"
                        },
                        "availability_365": {
                            "type": "number",
                            "title": "Yearly availibility",
                            "description": "Number of  days in a year for which the accommodation can be rented"
                        },
                        "filename": {
                            "type": "string",
                            "title": "filename",
                            "description": ""
                        },
                        "date": {
                            "type": "string",
                            "format": "date",
                            "title": "Date",
                            "description": ""
                        },
                        "country": {
                            "type": "string",
                            "title": "Country",
                            "description": ""
                        },
                        "city": {
                            "type": "string",
                            "title": "City",
                            "description": ""
                        },
                        "location": {
                            "type": "string",
                            "title": "Location",
                            "description": ""
                        },
                        "geo_shape": {
                            "type": "object",
                            "oneOf": [
                                {
                                    "$ref": "#/definitions/geometry"
                                }
                            ],
                            "title": "geo_shape",
                            "description": ""
                        },
                        "geo_point_2d": {
                            "type": "array",
                            "minItems": 2,
                            "maxItems": 2,
                            "items": {
                                "type": "number"
                            },
                            "title": "Geo Point",
                            "description": ""
                        }
                    }
                }
            }
        }
    }
}
