{
    "title": "deliberations-du-conseil-municipal@soissons",
    "type": "object",
    "oneOf": [
        {
            "$ref": "#/definitions/deliberations-du-conseil-municipal@soissons"
        }
    ],
    "definitions": {
        "deliberations-du-conseil-municipal@soissons": {
            "properties": {
                "records": {
                    "type": "array",
                    "items": {
                        "$ref": "#/definitions/deliberations-du-conseil-municipal@soissons_records"
                    }
                }
            }
        },
        "deliberations-du-conseil-municipal@soissons_records": {
            "properties": {
                "fields": {
                    "type": "object",
                    "properties": {
                        "ndeg_d_acte": {
                            "type": "string",
                            "title": "N° D'ACTE",
                            "description": ""
                        },
                        "theme": {
                            "type": "string",
                            "title": "THEME",
                            "description": ""
                        },
                        "titre": {
                            "type": "string",
                            "title": "TITRE",
                            "description": ""
                        },
                        "date": {
                            "type": "string",
                            "format": "date",
                            "title": "DATE",
                            "description": "date"
                        },
                        "fichier_media": {
                            "type": "string",
                            "title": "FICHIER MEDIA",
                            "description": ""
                        }
                    }
                }
            }
        }
    }
}
