{
    "title": "effectifs-de-la-fonction-publique-de-letat@opendatamef",
    "type": "object",
    "oneOf": [
        {
            "$ref": "#/definitions/effectifs-de-la-fonction-publique-de-letat@opendatamef"
        }
    ],
    "definitions": {
        "effectifs-de-la-fonction-publique-de-letat@opendatamef": {
            "properties": {
                "records": {
                    "type": "array",
                    "items": {
                        "$ref": "#/definitions/effectifs-de-la-fonction-publique-de-letat@opendatamef_records"
                    }
                }
            }
        },
        "effectifs-de-la-fonction-publique-de-letat@opendatamef_records": {
            "properties": {
                "fields": {
                    "type": "object",
                    "properties": {}
                }
            }
        }
    }
}
