{
    "title": "fr-en-complements-programmes-premier-degre@dataeducation",
    "type": "object",
    "oneOf": [
        {
            "$ref": "#/definitions/fr-en-complements-programmes-premier-degre@dataeducation"
        }
    ],
    "definitions": {
        "fr-en-complements-programmes-premier-degre@dataeducation": {
            "properties": {
                "records": {
                    "type": "array",
                    "items": {
                        "$ref": "#/definitions/fr-en-complements-programmes-premier-degre@dataeducation_records"
                    }
                }
            }
        },
        "fr-en-complements-programmes-premier-degre@dataeducation_records": {
            "properties": {
                "fields": {
                    "type": "object",
                    "properties": {
                        "descriptif": {
                            "type": "string",
                            "title": "Descriptif",
                            "description": "Description du complément"
                        },
                        "niveau_d_enseignement": {
                            "type": "string",
                            "title": "Niveau d'enseignement",
                            "description": "Niveau d'enseignement"
                        },
                        "nature_du_complement": {
                            "type": "string",
                            "title": "Nature du complément",
                            "description": "Attendus, repères annuels de progression, ..."
                        },
                        "discipline": {
                            "type": "string",
                            "title": "Discipline",
                            "description": "Discipline"
                        },
                        "texte_officiel": {
                            "type": "string",
                            "title": "Texte officiel",
                            "description": "Identification du texte officiel qui définit le complément au programme"
                        },
                        "lien_vers_le_texte_officiel": {
                            "type": "string",
                            "title": "Lien vers le texte officiel",
                            "description": "Lien vers le texte officiel qui définit le complément au programme"
                        },
                        "contenu": {
                            "type": "string",
                            "title": "Contenu",
                            "description": "Lien vers le complément aux programme"
                        },
                        "entre_en_vigueur_a_la_rentree": {
                            "type": "number",
                            "title": "Entre en vigueur à la rentrée",
                            "description": "Date d'entrée en vigueur du complement"
                        },
                        "abroge_a_la_rentree": {
                            "type": "string",
                            "title": "Abrogé à la rentrée",
                            "description": "Date d'abrogation du complément"
                        }
                    }
                }
            }
        }
    }
}
