{
    "title": "jddbeges2019aka_20220530@akajoule",
    "type": "object",
    "oneOf": [
        {
            "$ref": "#/definitions/jddbeges2019aka_20220530@akajoule"
        }
    ],
    "definitions": {
        "jddbeges2019aka_20220530@akajoule": {
            "properties": {
                "records": {
                    "type": "array",
                    "items": {
                        "$ref": "#/definitions/jddbeges2019aka_20220530@akajoule_records"
                    }
                }
            }
        },
        "jddbeges2019aka_20220530@akajoule_records": {
            "properties": {
                "fields": {
                    "type": "object",
                    "properties": {
                        "annee_beges": {
                            "type": "string",
                            "format": "date",
                            "title": "Année BEGES",
                            "description": ""
                        },
                        "perimetre": {
                            "type": "string",
                            "title": "Périmètre",
                            "description": ""
                        },
                        "secteur": {
                            "type": "string",
                            "title": "Secteur",
                            "description": ""
                        },
                        "sous_secteur": {
                            "type": "string",
                            "title": "Sous-secteur",
                            "description": ""
                        },
                        "operateur": {
                            "type": "string",
                            "title": "Opérateur",
                            "description": ""
                        },
                        "statut": {
                            "type": "string",
                            "title": "Statut",
                            "description": ""
                        },
                        "annee_donnees": {
                            "type": "string",
                            "format": "date",
                            "title": "Année données",
                            "description": ""
                        },
                        "categorie_base_carbone": {
                            "type": "string",
                            "title": "Catégorie\nBase Carbone",
                            "description": ""
                        },
                        "sous_categorie": {
                            "type": "string",
                            "title": "Sous-catégorie",
                            "description": ""
                        },
                        "grandeur_base_carbone": {
                            "type": "string",
                            "title": "Grandeur\nBase Carbone",
                            "description": ""
                        },
                        "poste": {
                            "type": "string",
                            "title": "Poste",
                            "description": ""
                        },
                        "valeur": {
                            "type": "number",
                            "title": "Valeur",
                            "description": ""
                        },
                        "unite": {
                            "type": "string",
                            "title": "Unité",
                            "description": ""
                        },
                        "scope_1_f_e": {
                            "type": "number",
                            "title": "Scope 1\nF.E.",
                            "description": ""
                        },
                        "scope_1_emissions": {
                            "type": "number",
                            "title": "Scope 1\nEmissions",
                            "description": ""
                        },
                        "scope_2_f_e": {
                            "type": "number",
                            "title": "Scope 2\nF.E.",
                            "description": ""
                        },
                        "scope_2_emissions": {
                            "type": "number",
                            "title": "Scope 2\nEmissions",
                            "description": ""
                        },
                        "scope_3_f_e": {
                            "type": "number",
                            "title": "Scope 3\nF.E.",
                            "description": ""
                        },
                        "scope_3_emissions": {
                            "type": "number",
                            "title": "Scope 3\nEmissions",
                            "description": ""
                        },
                        "emissions_scopes_1_2_kgco2e": {
                            "type": "number",
                            "title": "Emissions Scopes 1 & 2 (kgCO2e)",
                            "description": ""
                        },
                        "emissions_totales_kgco2e": {
                            "type": "number",
                            "title": "Emissions totales (kgCO2e)",
                            "description": ""
                        },
                        "emissions_tco2e": {
                            "type": "number",
                            "title": "Emissions (tCO2e)",
                            "description": ""
                        },
                        "colonne1": {
                            "type": "string",
                            "title": "Colonne1",
                            "description": ""
                        },
                        "remarque": {
                            "type": "string",
                            "title": "Remarque",
                            "description": ""
                        },
                        "contact": {
                            "type": "string",
                            "title": "Contact",
                            "description": ""
                        },
                        "emissions_scopes_1_2_tco2e": {
                            "type": "number",
                            "title": "Emissions Scopes 1 & 2 (tCO2e)",
                            "description": ""
                        },
                        "emissions_scope_3_tco2e": {
                            "type": "number",
                            "title": "Emissions Scope 3 (tCO2e)",
                            "description": ""
                        },
                        "isscope1or2": {
                            "type": "string",
                            "title": "isScope1or2",
                            "description": ""
                        },
                        "isscope3": {
                            "type": "string",
                            "title": "isScope3",
                            "description": ""
                        }
                    }
                }
            }
        }
    }
}
