{
    "title": "la-qualite-des-eaux-de-baignade-en-eau-douce-en-2015@occitanie",
    "type": "object",
    "oneOf": [
        {
            "$ref": "#/definitions/la-qualite-des-eaux-de-baignade-en-eau-douce-en-2015@occitanie"
        }
    ],
    "definitions": {
        "la-qualite-des-eaux-de-baignade-en-eau-douce-en-2015@occitanie": {
            "properties": {
                "records": {
                    "type": "array",
                    "items": {
                        "$ref": "#/definitions/la-qualite-des-eaux-de-baignade-en-eau-douce-en-2015@occitanie_records"
                    }
                }
            }
        },
        "la-qualite-des-eaux-de-baignade-en-eau-douce-en-2015@occitanie_records": {
            "properties": {
                "fields": {
                    "type": "object",
                    "properties": {
                        "empty": {
                            "type": "string",
                            "title": "départements",
                            "description": ""
                        },
                        "nombre_total_de_points_de_releves_en_eau_douce": {
                            "type": "string",
                            "title": "Nombre total de points de releves en eau douce ",
                            "description": ""
                        },
                        "eau_d_excellente_qualite": {
                            "type": "string",
                            "title": "Eau d'excellente qualite ",
                            "description": ""
                        },
                        "eau_de_bonne_qualite": {
                            "type": "string",
                            "title": "Eau de bonne qualite ",
                            "description": ""
                        },
                        "eau_de_qualite_suffisante": {
                            "type": "string",
                            "title": "Eau de qualite suffisante ",
                            "description": ""
                        },
                        "eau_de_qualite_insuffisante": {
                            "type": "string",
                            "title": "Eau de qualite insuffisante ",
                            "description": ""
                        },
                        "points_non_classes": {
                            "type": "string",
                            "title": "Points non classes ",
                            "description": ""
                        },
                        "total": {
                            "type": "string",
                            "title": "Total ",
                            "description": ""
                        }
                    }
                }
            }
        }
    }
}
