{
    "title": "ma-discipline-artistique-dans-quel-conservatoire-du-territoire-@issy-les-moulineaux",
    "type": "object",
    "oneOf": [
        {
            "$ref": "#/definitions/ma-discipline-artistique-dans-quel-conservatoire-du-territoire-@issy-les-moulineaux"
        }
    ],
    "definitions": {
        "ma-discipline-artistique-dans-quel-conservatoire-du-territoire-@issy-les-moulineaux": {
            "properties": {
                "records": {
                    "type": "array",
                    "items": {
                        "$ref": "#/definitions/ma-discipline-artistique-dans-quel-conservatoire-du-territoire-@issy-les-moulineaux_records"
                    }
                }
            }
        },
        "ma-discipline-artistique-dans-quel-conservatoire-du-territoire-@issy-les-moulineaux_records": {
            "properties": {
                "fields": {
                    "type": "object",
                    "properties": {
                        "type": {
                            "type": "string",
                            "title": "Type",
                            "description": ""
                        },
                        "discipline": {
                            "type": "string",
                            "title": "Discipline",
                            "description": ""
                        },
                        "conservatoire_concerne": {
                            "type": "string",
                            "title": "Conservatoire concerné",
                            "description": ""
                        },
                        "presence_de_la_discipline": {
                            "type": "string",
                            "title": "Présence de la discipline",
                            "description": ""
                        },
                        "id": {
                            "type": "string",
                            "title": "ID",
                            "description": ""
                        }
                    }
                }
            }
        }
    }
}
