{
    "title": "parcelles-cadastrals-durbana-amb-fitxa-urbanistica@valencia",
    "type": "object",
    "oneOf": [
        {
            "$ref": "#/definitions/parcelles-cadastrals-durbana-amb-fitxa-urbanistica@valencia"
        }
    ],
    "definitions": {
        "parcelles-cadastrals-durbana-amb-fitxa-urbanistica@valencia": {
            "properties": {
                "records": {
                    "type": "array",
                    "items": {
                        "$ref": "#/definitions/parcelles-cadastrals-durbana-amb-fitxa-urbanistica@valencia_records"
                    }
                }
            }
        },
        "parcelles-cadastrals-durbana-amb-fitxa-urbanistica@valencia_records": {
            "properties": {
                "fields": {
                    "type": "object",
                    "properties": {
                        "refpar": {
                            "type": "integer",
                            "title": "﻿refpar",
                            "description": ""
                        },
                        "refpla": {
                            "type": "string",
                            "title": "refpla",
                            "description": ""
                        },
                        "codvia": {
                            "type": "integer",
                            "title": "codvia",
                            "description": ""
                        },
                        "npol": {
                            "type": "integer",
                            "title": "npol",
                            "description": ""
                        },
                        "dupli": {
                            "type": "string",
                            "title": "dupli",
                            "description": ""
                        },
                        "construccion": {
                            "type": "string",
                            "title": "construccion",
                            "description": ""
                        },
                        "antiguedad": {
                            "type": "string",
                            "title": "antiguedad",
                            "description": ""
                        },
                        "reforma": {
                            "type": "string",
                            "title": "reforma",
                            "description": ""
                        },
                        "tipo_reforma": {
                            "type": "string",
                            "title": "tipo_reforma",
                            "description": ""
                        },
                        "coorx": {
                            "type": "number",
                            "title": "coorx",
                            "description": ""
                        },
                        "coory": {
                            "type": "number",
                            "title": "coory",
                            "description": ""
                        },
                        "poblacion_total": {
                            "type": "integer",
                            "title": "poblacion_total",
                            "description": ""
                        },
                        "poblacion_0_14": {
                            "type": "integer",
                            "title": "poblacion_0_14",
                            "description": ""
                        },
                        "poblacion_15_65": {
                            "type": "integer",
                            "title": "poblacion_15_65",
                            "description": ""
                        },
                        "poblacion_66_o_mas": {
                            "type": "integer",
                            "title": "poblacion_66_o_mas",
                            "description": ""
                        },
                        "refcat": {
                            "type": "string",
                            "title": "refcat",
                            "description": ""
                        }
                    }
                }
            }
        }
    }
}
