{
    "title": "wanderwege-wms@stgallen",
    "type": "object",
    "oneOf": [
        {
            "$ref": "#/definitions/wanderwege-wms@stgallen"
        }
    ],
    "definitions": {
        "wanderwege-wms@stgallen": {
            "properties": {
                "records": {
                    "type": "array",
                    "items": {
                        "$ref": "#/definitions/wanderwege-wms@stgallen_records"
                    }
                }
            }
        },
        "wanderwege-wms@stgallen_records": {
            "properties": {
                "fields": {
                    "type": "object",
                    "properties": {}
                }
            }
        }
    }
}
