{
    "title": "mouvements-sociaux-depuis-1994",
    "type": "object",
    "oneOf": [
        {
            "$ref": "#/definitions/mouvements-sociaux-depuis-1994"
        }
    ],
    "definitions": {
        "mouvements-sociaux-depuis-1994": {
            "properties": {
                "records": {
                    "type": "array",
                    "items": {
                        "$ref": "#/definitions/mouvements-sociaux-depuis-1994_records"
                    }
                }
            }
        },
        "mouvements-sociaux-depuis-1994_records": {
            "properties": {
                "fields": {
                    "type": "object",
                    "properties": {
                        "date": {
                            "type": "string",
                            "format": "date",
                            "title": "Date",
                            "description": ""
                        },
                        "journees_perdues": {
                            "type": "number",
                            "title": "Journées perdues",
                            "description": ""
                        }
                    }
                }
            }
        }
    }
}
